ArtByCode/__init__.py
ArtByCode/abc.py
ArtByCode-0.0.5.dist-info/LICENSE.txt
ArtByCode-0.0.5.dist-info/METADATA
ArtByCode-0.0.5.dist-info/WHEEL
ArtByCode-0.0.5.dist-info/top_level.txt
ArtByCode-0.0.5.dist-info/RECORD
