Metadata-Version: 2.1
Name: ArtByCode
Version: 0.0.5
Summary: ArtByCode
Author: Coder Artist
Author-email: abc4artbycode@gmail.com
Keywords: python,sketch,drawing,animation,code hub,pencil sketch,painting
Classifier: Development Status :: 1 - Planning
Classifier: Programming Language :: Python :: 3
Classifier: Operating System :: Microsoft :: Windows
License-File: LICENSE.txt
Requires-Dist: turtle (==0.0.1)
Requires-Dist: docx
Requires-Dist: python-docx
Requires-Dist: requests
